Metadata-Version: 2.4
Name: gemini-code
Version: 0.1.105
Summary: An AI coding assistant CLI using Google's Gemini models with function calling.
Author-email: Raiza Martin <raiza@huxe.ai>
License-Expression: MIT
Project-URL: Homepage, https://github.com/raizamartin/gemini-code
Project-URL: Bug Tracker, https://github.com/raizamartin/gemini-code/issues
Classifier: Programming Language :: Python :: 3
Classifier: Operating System :: OS Independent
Classifier: Development Status :: 3 - Alpha
Classifier: Environment :: Console
Classifier: Intended Audience :: Developers
Classifier: Topic :: Software Development
Classifier: Topic :: Utilities
Requires-Python: >=3.9
Requires-Dist: google-generativeai>=0.5.0
Requires-Dist: click>=8.0
Requires-Dist: rich>=13.0
Requires-Dist: PyYAML>=6.0
Requires-Dist: tiktoken>=0.6.0
Requires-Dist: questionary>=2.0.0
